{"accuracy": 0.9029272492466638, "precision": 0.9028611956181776, "recall": 0.9029272492466638,
 "f1_score": 0.9025834156123671, 
 "confusion_matrix": [[2424, 17, 584, 104], [28, 2646, 353, 99], [449, 408, 19284, 1258], [41, 61, 657, 13401]],
  "classification_report": "              precision    recall  f1-score   support\n\n    hypernym       0.82      0.77      0.80      3129\n     hyponym       0.84      0.85      0.85      3126\n        none       0.92      0.90      0.91     21399\n    synonymy       0.90      0.95      0.92     14160\n\n    accuracy                           0.90     41814\n   macro avg       0.87      0.87      0.87     41814\nweighted avg       0.90      0.90      0.90     41814\n",
   "timestamp": 1724519070, "checkpoint_dir_name": null, "done": false, "training_iteration": 1, "trial_id": "6d23f_00001", "date": "2024-08-24_20-04-30", "time_this_iter_s": 115.53001070022583, "time_total_s": 115.53001070022583, "pid": 2348, "hostname": "Davidovic", "node_ip": "127.0.0.1",
    "config": {"lr": 0.001, "num_epochs": 20, "batch_size": 128, "hidden_sizes": [512, 256, 128, 64], "activation": "relu", "optimizer": "Adam", "dropout_rate": 0.0, "postive_percentage": 0.6}, "time_since_restore": 115.53001070022583, "iterations_since_restore": 1}
